README.md
TLSSigAPIv2.py
setup.py
tls_sig_api_v2.egg-info/PKG-INFO
tls_sig_api_v2.egg-info/SOURCES.txt
tls_sig_api_v2.egg-info/dependency_links.txt
tls_sig_api_v2.egg-info/top_level.txt