Metadata-Version: 1.0
Name: tls-sig-api-v2
Version: 1.1
Summary: tls-sig-api-v2 适用于腾讯云通信生成用户账号签名。
Home-page: https://github.com/tencentyun/tls-sig-api-v2-python
Author: weijunyi
Author-email: weijunyi@tencent.com
License: MIT Licence
Platform: any
